{
    "uplink": {
        "trace_pattern": [
            {
                "duration": 1126,
                "capacity": 7.073712255772646
            },
            {
                "duration": 10126,
                "capacity": 0.3812956745012838
            },
            {
                "duration": 3786,
                "capacity": 7.39540412044374
            },
            {
                "duration": 1279,
                "capacity": 2.1391712275215014
            },
            {
                "duration": 4698,
                "capacity": 0.29118773946360155
            },
            {
                "duration": 1318,
                "capacity": 2.0758725341426403
            },
            {
                "duration": 1445,
                "capacity": 1.893425605536332
            },
            {
                "duration": 1017,
                "capacity": 4.035398230088496
            },
            {
                "duration": 3563,
                "capacity": 2.68762278978389
            },
            {
                "duration": 6918,
                "capacity": 0.19774501300954034
            },
            {
                "duration": 5301,
                "capacity": 0.25806451612903225
            },
            {
                "duration": 1798,
                "capacity": 2.2825361512791993
            },
            {
                "duration": 1441,
                "capacity": 7.59472588480222
            },
            {
                "duration": 1200,
                "capacity": 9.12
            },
            {
                "duration": 1238,
                "capacity": 2.210016155088853
            },
            {
                "duration": 1360,
                "capacity": 9.052941176470588
            },
            {
                "duration": 1140,
                "capacity": 8.4
            },
            {
                "duration": 1001,
                "capacity": 8.1998001998002
            },
            {
                "duration": 1022,
                "capacity": 6.692759295499021
            },
            {
                "duration": 1116,
                "capacity": 8.580645161290322
            },
            {
                "duration": 1084,
                "capacity": 7.571955719557195
            },
            {
                "duration": 1098,
                "capacity": 13.704918032786885
            },
            {
                "duration": 1141,
                "capacity": 8.392638036809815
            },
            {
                "duration": 1039,
                "capacity": 6.5832531280077
            },
            {
                "duration": 1080,
                "capacity": 11.846296296296297
            },
            {
                "duration": 1001,
                "capacity": 9.566433566433567
            },
            {
                "duration": 1098,
                "capacity": 8.721311475409836
            },
            {
                "duration": 1278,
                "capacity": 4.28169014084507
            },
            {
                "duration": 1020,
                "capacity": 6.705882352941177
            },
            {
                "duration": 1223,
                "capacity": 7.829926410466067
            },
            {
                "duration": 1621,
                "capacity": 8.439235040098705
            },
            {
                "duration": 1176,
                "capacity": 12.795918367346939
            },
            {
                "duration": 1043,
                "capacity": 6.5580057526366256
            },
            {
                "duration": 1117,
                "capacity": 7.348254252461952
            },
            {
                "duration": 1045,
                "capacity": 7.8545454545454545
            },
            {
                "duration": 1197,
                "capacity": 6.857142857142857
            },
            {
                "duration": 1261,
                "capacity": 6.509119746233148
            },
            {
                "duration": 1338,
                "capacity": 6.134529147982063
            },
            {
                "duration": 1003,
                "capacity": 2.7278165503489533
            },
            {
                "duration": 8723,
                "capacity": 1.0977874584431961
            },
            {
                "duration": 1116,
                "capacity": 48.238351254480285
            },
            {
                "duration": 1101,
                "capacity": 16.59037238873751
            },
            {
                "duration": 1077,
                "capacity": 15.242339832869082
            },
            {
                "duration": 1080,
                "capacity": 8.866666666666667
            },
            {
                "duration": 1080,
                "capacity": 8.866666666666667
            },
            {
                "duration": 1063,
                "capacity": 9.008466603951081
            },
            {
                "duration": 1080,
                "capacity": 11.4
            },
            {
                "duration": 1078,
                "capacity": 12.690166975881262
            },
            {
                "duration": 1058,
                "capacity": 11.637051039697543
            },
            {
                "duration": 1061,
                "capacity": 10.314797360980208
            },
            {
                "duration": 1081,
                "capacity": 11.38945420906568
            },
            {
                "duration": 1019,
                "capacity": 8.0549558390579
            },
            {
                "duration": 1159,
                "capacity": 12.98360655737705
            },
            {
                "duration": 1020,
                "capacity": 13.411764705882353
            },
            {
                "duration": 1481,
                "capacity": 10.811613774476704
            },
            {
                "duration": 1061,
                "capacity": 15.472196041470312
            },
            {
                "duration": 1117,
                "capacity": 11.022381378692927
            },
            {
                "duration": 1422,
                "capacity": 11.713080168776372
            },
            {
                "duration": 1080,
                "capacity": 15.2
            },
            {
                "duration": 1020,
                "capacity": 14.75294117647059
            },
            {
                "duration": 1139,
                "capacity": 13.211589113257244
            },
            {
                "duration": 1202,
                "capacity": 15.933444259567388
            },
            {
                "duration": 1259,
                "capacity": 5.837966640190627
            },
            {
                "duration": 1001,
                "capacity": 13.666333666333667
            },
            {
                "duration": 1117,
                "capacity": 13.471799462846912
            },
            {
                "duration": 3075,
                "capacity": 1.7795121951219512
            },
            {
                "duration": 1437,
                "capacity": 28.698677800974252
            },
            {
                "duration": 1099,
                "capacity": 12.447679708826206
            },
            {
                "duration": 1121,
                "capacity": 13.423728813559322
            },
            {
                "duration": 1039,
                "capacity": 13.1665062560154
            },
            {
                "duration": 1222,
                "capacity": 14.553191489361701
            },
            {
                "duration": 1118,
                "capacity": 9.566189624329159
            },
            {
                "duration": 1061,
                "capacity": 14.182846371347786
            },
            {
                "duration": 1040,
                "capacity": 13.153846153846153
            },
            {
                "duration": 1037,
                "capacity": 13.191899710703954
            },
            {
                "duration": 1043,
                "capacity": 10.000958772770852
            },
            {
                "duration": 1058,
                "capacity": 16.80907372400756
            },
            {
                "duration": 1043,
                "capacity": 11.804410354745926
            },
            {
                "duration": 1237,
                "capacity": 16.58852061438965
            },
            {
                "duration": 1120,
                "capacity": 12.214285714285714
            },
            {
                "duration": 1019,
                "capacity": 8.307163886162904
            },
            {
                "duration": 1063,
                "capacity": 15.443085606773284
            },
            {
                "duration": 1080,
                "capacity": 12.666666666666666
            },
            {
                "duration": 1380,
                "capacity": 8.407246376811594
            },
            {
                "duration": 1057,
                "capacity": 12.94228949858089
            },
            {
                "duration": 1061,
                "capacity": 11.604147031102734
            },
            {
                "duration": 1081,
                "capacity": 11.38945420906568
            },
            {
                "duration": 1139,
                "capacity": 12.025460930640913
            },
            {
                "duration": 1040,
                "capacity": 7.660576923076923
            },
            {
                "duration": 1139,
                "capacity": 12.010535557506584
            },
            {
                "duration": 1020,
                "capacity": 14.75294117647059
            },
            {
                "duration": 1080,
                "capacity": 12.666666666666666
            },
            {
                "duration": 1194,
                "capacity": 8.032663316582914
            },
            {
                "duration": 1049,
                "capacity": 14.345090562440419
            },
            {
                "duration": 1180,
                "capacity": 13.91186440677966
            },
            {
                "duration": 2060,
                "capacity": 1.3281553398058252
            },
            {
                "duration": 1140,
                "capacity": 27.70964912280702
            },
            {
                "duration": 1139,
                "capacity": 8.407374890254609
            },
            {
                "duration": 1025,
                "capacity": 12.01170731707317
            },
            {
                "duration": 1113,
                "capacity": 13.520215633423181
            },
            {
                "duration": 4621,
                "capacity": 5.025752001731227
            },
            {
                "duration": 17602,
                "capacity": 1.8647312805363028
            },
            {
                "duration": 1379,
                "capacity": 2.9760696156635245
            },
            {
                "duration": 1320,
                "capacity": 4.1454545454545455
            },
            {
                "duration": 1100,
                "capacity": 8.705454545454545
            },
            {
                "duration": 1001,
                "capacity": 8.1998001998002
            },
            {
                "duration": 1056,
                "capacity": 10.363636363636363
            },
            {
                "duration": 1062,
                "capacity": 10.305084745762711
            },
            {
                "duration": 2058,
                "capacity": 3.237609329446064
            },
            {
                "duration": 1381,
                "capacity": 3.9623461259956554
            },
            {
                "duration": 1260,
                "capacity": 9.771428571428572
            },
            {
                "duration": 1079,
                "capacity": 6.3392029657089894
            },
            {
                "duration": 1241,
                "capacity": 6.614020950846092
            },
            {
                "duration": 1061,
                "capacity": 6.44674835061263
            },
            {
                "duration": 1057,
                "capacity": 6.471144749290445
            },
            {
                "duration": 1043,
                "capacity": 6.5580057526366256
            },
            {
                "duration": 1699,
                "capacity": 2.8846380223660977
            },
            {
                "duration": 1172,
                "capacity": 10.505119453924914
            },
            {
                "duration": 1242,
                "capacity": 8.81159420289855
            },
            {
                "duration": 1278,
                "capacity": 5.352112676056338
            },
            {
                "duration": 1961,
                "capacity": 2.0928097909229986
            },
            {
                "duration": 1079,
                "capacity": 5.071362372567192
            },
            {
                "duration": 961,
                "capacity": 5.694068678459938
            }
        ]
    },
    "type": "video",
    "downlink": {}
}